{
"type": "FeatureCollection",
"name": "UNIV_OKE",
"crs": { "type": "name", "properties": { "name": "urn:ogc:def:crs:OGC:1.3:CRS84" } },
"features": [
{ "type": "Feature", "properties": { "Id": 0, "Nama": "Universitas Gadjah Mada" }, "geometry": { "type": "Point", "coordinates": [ 110.377478403030523, -7.769521614656743 ] } },
{ "type": "Feature", "properties": { "Id": 0, "Nama": "Universitas Negeri Yogyakarta" }, "geometry": { "type": "Point", "coordinates": [ 110.38608354551279, -7.772741154287873 ] } },
{ "type": "Feature", "properties": { "Id": 0, "Nama": "Universitas Islam Indonesia" }, "geometry": { "type": "Point", "coordinates": [ 110.413706989984746, -7.686728843502722 ] } },
{ "type": "Feature", "properties": { "Id": 0, "Nama": "UIN Sunan Kalijaga Yogyakarta" }, "geometry": { "type": "Point", "coordinates": [ 110.394335177959093, -7.78481661700003 ] } },
{ "type": "Feature", "properties": { "Id": 0, "Nama": "Universitas Aisyiyah Yogyakarta" }, "geometry": { "type": "Point", "coordinates": [ 110.333597599391794, -7.768469679617981 ] } },
{ "type": "Feature", "properties": { "Id": 0, "Nama": "UPN Veteran Yogyakarta" }, "geometry": { "type": "Point", "coordinates": [ 110.409781875608132, -7.762273619888326 ] } },
{ "type": "Feature", "properties": { "Id": 0, "Nama": "Universitas Sanatha Darma" }, "geometry": { "type": "Point", "coordinates": [ 110.389332856965922, -7.775296167644879 ] } }
]
}
